pyamlside2/__init__.py
pyamlside2/create_widgets.py
pyamlside2/label_configure.py
pyamlside2/load_yaml.py
pyamlside2/mainwindow.py
pyamlside2/drawio_parse/__init__.py
pyamlside2/drawio_parse/parse.py
pyamlside2/drawio_parse/propaties_class.py
pyamlside2/utils/__init__.py
pyamlside2/utils/get_yaml.py
yaml/calculator.yaml
yaml/chaos.yaml
yaml/header.yaml
yaml/color/style_blue.yaml
yaml/color/style_green.yaml
yaml/color/style_red.yaml
yaml/rect/basic_button.yaml
pyamlside2-0.3.1.dist-info/METADATA
pyamlside2-0.3.1.dist-info/WHEEL
pyamlside2-0.3.1.dist-info/entry_points.txt
pyamlside2-0.3.1.dist-info/top_level.txt
pyamlside2-0.3.1.dist-info/RECORD
