Metadata-Version: 2.1
Name: pyamlside2
Version: 0.3.1
Summary: PySide2 configuration in yaml format providing the most simple script.
Home-page: https://github.com/Ar-Ray-code/ReadableWidgets
Author: Ar-Ray-code
Author-email: ray255ar@gmail.com
License: MIT
Project-URL: Source, https://github.com/Ar-Ray-code/ReadableWidgets
Project-URL: Tracker, https://github.com/Ar-Ray-code/ReadableWidgets/issues
Keywords: PySide2 yaml
Platform: UNKNOWN
Classifier: License :: OSI Approved :: MIT License
Classifier: Programming Language :: Python :: 3.8
Classifier: Programming Language :: Python :: 3.9
Requires-Python: >=3.8
Requires-Dist: PySide2
Requires-Dist: PyYAML
